globus_action_provider_tools_fastapi/__init__.py
globus_action_provider_tools_fastapi/async_helpers.py
globus_action_provider_tools_fastapi/dynamo_persistence.py
globus_action_provider_tools_fastapi/fastapi_action_provider_exceptions.py
globus_action_provider_tools_fastapi/fastapi_router.py
globus_action_provider_tools_fastapi/in_memory_persistence.py
globus_action_provider_tools_fastapi/persistence.py
globus_action_provider_tools_fastapi/py.typed
globus_action_provider_tools_fastapi/sqlmodel_persistence.py
globus_action_provider_tools_fastapi-0.1.0a2.dist-info/WHEEL
globus_action_provider_tools_fastapi-0.1.0a2.dist-info/METADATA
globus_action_provider_tools_fastapi-0.1.0a2.dist-info/RECORD
