Metadata-Version: 2.1
Name: globus-action-provider-tools-fastapi
Version: 0.1.0a2
Summary: 
Author: Jim Pruyne
Author-email: pruyne@uchicago.edu
Requires-Python: >=3.8,<4.0
Classifier: Programming Language :: Python :: 3
Classifier: Programming Language :: Python :: 3.10
Classifier: Programming Language :: Python :: 3.8
Classifier: Programming Language :: Python :: 3.9
Requires-Dist: arrow (>=1,<2)
Requires-Dist: fastapi (>=0.78,<0.79)
Requires-Dist: globus-action-provider-tools (>=0.12.0,<0.13.0)
